README.md
setup.py
examgen/__init__.py
examgen/cli.py
examgen/examgen.py
examgen/main.py
examgen/mainbatch.py
examgen.egg-info/PKG-INFO
examgen.egg-info/SOURCES.txt
examgen.egg-info/dependency_links.txt
examgen.egg-info/entry_points.txt
examgen.egg-info/requires.txt
examgen.egg-info/top_level.txt
examgen/template/exam-template.md
examgen/template/question-template.md
examgen/template/style.css