Metadata-Version: 2.1
Name: examgen
Version: 0.1.1
Summary: Generate exams using Markdown and Python
Home-page: https://github.com/yurimalheiros/examgen
Author: Yuri Malheiros
Author-email: yuri@dcx.ufpb.br
License: UNKNOWN
Platform: UNKNOWN
Classifier: Programming Language :: Python :: 3
Classifier: License :: OSI Approved :: MIT License
Classifier: Operating System :: OS Independent
